simple_rest_framework/__init__.py
simple_rest_framework/exceptions.py
simple_rest_framework/services.py
simple_rest_framework/views.py
simple_rest_framework-0.5.2.dist-info/METADATA
simple_rest_framework-0.5.2.dist-info/WHEEL
simple_rest_framework-0.5.2.dist-info/top_level.txt
simple_rest_framework-0.5.2.dist-info/RECORD
