Metadata-Version: 2.1
Name: simple_rest_framework
Version: 0.5.2
Summary: Esta libreria permite agilizar el desarrollo de APIs REST en Django. Manejando un CRUD básico de forma automática y manejando excepciones de forma sencilla.
Home-page: https://github.com/ValentinCabrera/simple_rest_framework
Author: Valentin Cabrera
Author-email: valentincabrera2003@gmail.com
Classifier: Programming Language :: Python :: 3
Classifier: License :: OSI Approved :: MIT License
Classifier: Operating System :: OS Independent
Requires-Python: >=3.6
Requires-Dist: djangorestframework
